leggedsnake/__init__.py
leggedsnake/dynamiclinkage.py
leggedsnake/geneticoptimizer.py
leggedsnake/physicsengine.py
leggedsnake/show_evolution.py
leggedsnake/utility.py
leggedsnake/walker.py
leggedsnake/worldvisualizer.py
leggedsnake-0.4.0.dist-info/LICENSE.rst
leggedsnake-0.4.0.dist-info/METADATA
leggedsnake-0.4.0.dist-info/WHEEL
leggedsnake-0.4.0.dist-info/top_level.txt
leggedsnake-0.4.0.dist-info/zip-safe
leggedsnake-0.4.0.dist-info/RECORD
