Metadata-Version: 2.1
Name: leggedsnake
Version: 0.4.0
Summary: Simulate and optimize planar leg mechanisms using PSO and GA
Home-page: https://hugofara.github.io/leggedsnake/
Author: Hugo Farajallah
Author-email: Hugo Farajallah <leggedsnake@hugofara.net>
License: MIT License
Project-URL: Homepage, https://hugofara.net/leggedsnake-retro-ingeneering-evolution/
Project-URL: Documentation, https://github.com/HugoFara/leggedsnake/blob/main/CHANGELOG.md
Project-URL: Repository, https://github.com/HugoFara/leggedsnake
Project-URL: Changelog, https://github.com/me/spam/blob/master/CHANGELOG.md
Keywords: linkage,leg mechanism,optimization,leggedsnake,walking linkage
Classifier: Development Status :: 4 - Beta
Classifier: Programming Language :: Python :: 3
Classifier: Topic :: Scientific/Engineering
Classifier: Topic :: Scientific/Engineering :: Artificial Life
Classifier: Programming Language :: Python :: 3
Classifier: Programming Language :: Python :: 3.7
Classifier: Programming Language :: Python :: 3.8
Classifier: Programming Language :: Python :: 3.9
Classifier: Programming Language :: Python :: 3.10
Classifier: Programming Language :: Python :: 3.11
Classifier: Environment :: Console
Classifier: Intended Audience :: Science/Research
Classifier: Intended Audience :: Legal Industry
Classifier: Intended Audience :: End Users/Desktop
Classifier: Operating System :: OS Independent
Requires-Python: >=3.7
License-File: LICENSE.rst
Requires-Dist: numpy
Requires-Dist: tqdm
Requires-Dist: matplotlib
Requires-Dist: pylinkage
